klaradvn/__init__.py
klaradvn/build_model.py
klaradvn/cli.py
klaradvn/extract.py
klaradvn/generate.py
klaradvn/template.modelfile
klaradvn-0.1.0.dist-info/METADATA
klaradvn-0.1.0.dist-info/WHEEL
klaradvn-0.1.0.dist-info/entry_points.txt
klaradvn-0.1.0.dist-info/RECORD
