Metadata-Version: 2.1
Name: klaradvn
Version: 0.1.0
Summary: 
Author: Tom Laumen
Author-email: tom_laumen@hotmail.com
Requires-Python: >=3.11,<4.0
Classifier: Programming Language :: Python :: 3
Classifier: Programming Language :: Python :: 3.11
Classifier: Programming Language :: Python :: 3.12
Requires-Dist: ollama (>=0.4.8,<0.5.0)
Requires-Dist: pytest (>=8.3.5,<9.0.0)
Requires-Dist: typer (>=0.15.3,<0.16.0)
